README.rst
setup.py
python_qgenda.egg-info/PKG-INFO
python_qgenda.egg-info/SOURCES.txt
python_qgenda.egg-info/dependency_links.txt
python_qgenda.egg-info/requires.txt
python_qgenda.egg-info/top_level.txt
qgenda/__init__.py
qgenda/helpers.py
qgenda/settings.py
qgenda/api/__init__.py
qgenda/api/client.py
qgenda/api/exceptions.py
qgenda/cache/__init__.py
qgenda/cache/memcache.py
qgenda/cache/mock.py
qgenda/cache/redis.py
qgenda/pipeline/__init__.py
qgenda/pipeline/handlers.py
qgenda/pipeline/pipelines.py
qgenda/pipeline/post.py
qgenda/pipeline/pre.py
qgenda/tests/__init__.py
qgenda/tests/test_exceptions.py
qgenda/tests/test_get_methods.py
qgenda/tests/test_shared_auth.py