Metadata-Version: 2.1
Name: python-qgenda
Version: 1.0.dev5
Summary: Python client for QGenda REST API
Home-page: https://github.com/jjorissen52/python-qgenda
Author: JP Jorissen
Author-email: jjorissen52@gmail.com
Maintainer: JP Jorissen
Maintainer-email: jjorissen52@gmail.com
License: Apache
Keywords: QGenda,python api,python client
Platform: UNKNOWN
Classifier: Development Status :: 3 - Alpha
Classifier: Intended Audience :: Developers
Classifier: License :: OSI Approved :: Apache Software License
Classifier: Operating System :: OS Independent
Classifier: Programming Language :: Python :: 3.6
Classifier: Programming Language :: Python :: 3.7
Provides-Extra: memcache
Provides-Extra: redis
